sheetrika/__init__.py
sheetrika/cli.py
sheetrika/errors.py
sheetrika/filters.py
sheetrika/goo.py
sheetrika/loader.py
sheetrika/models.py
sheetrika/ym.py
sheetrika-0.1.5.dist-info/METADATA
sheetrika-0.1.5.dist-info/WHEEL
sheetrika-0.1.5.dist-info/entry_points.txt
sheetrika-0.1.5.dist-info/licenses/LICENSE
sheetrika-0.1.5.dist-info/RECORD
