Metadata-Version: 2.4
Name: sheetrika
Version: 0.1.5
Summary: 
License-File: LICENSE
Author: Dmitry Izosimov
Author-email: izosimdima@gmail.com
Requires-Python: >=3.12,<4.0
Classifier: Programming Language :: Python :: 3
Classifier: Programming Language :: Python :: 3.12
Classifier: Programming Language :: Python :: 3.13
Classifier: Programming Language :: Python :: 3.14
Requires-Dist: google-api-python-client (>=2.177.0,<3.0.0)
Requires-Dist: prettytable (>=3.16.0,<4.0.0)
Requires-Dist: pyyaml (>=6.0.2,<7.0.0)
